notte_browser/__init__.py
notte_browser/captcha.py
notte_browser/controller.py
notte_browser/errors.py
notte_browser/form_filling.py
notte_browser/playwright.py
notte_browser/playwright_async_api.py
notte_browser/py.typed
notte_browser/resolution.py
notte_browser/session.py
notte_browser/vault.py
notte_browser/window.py
notte_browser/workflow_variables.py
notte_browser/action_selection/__init__.py
notte_browser/action_selection/pipe.py
notte_browser/dom/__init__.py
notte_browser/dom/buildDomNode.js
notte_browser/dom/csspaths.py
notte_browser/dom/dropdown_menu.py
notte_browser/dom/id_generation.py
notte_browser/dom/locate.py
notte_browser/dom/parsing.py
notte_browser/dom/types.py
notte_browser/rendering/__init__.py
notte_browser/rendering/interaction_only.py
notte_browser/rendering/json.py
notte_browser/rendering/markdown.py
notte_browser/rendering/pipe.py
notte_browser/rendering/pruning.py
notte_browser/scraping/__init__.py
notte_browser/scraping/images.py
notte_browser/scraping/markdown.py
notte_browser/scraping/pipe.py
notte_browser/scraping/pruning.py
notte_browser/scraping/schema.py
notte_browser/tagging/__init__.py
notte_browser/tagging/page.py
notte_browser/tagging/type.py
notte_browser/tagging/action/__init__.py
notte_browser/tagging/action/base.py
notte_browser/tagging/action/pipe.py
notte_browser/tagging/action/llm_taging/__init__.py
notte_browser/tagging/action/llm_taging/base.py
notte_browser/tagging/action/llm_taging/listing.py
notte_browser/tagging/action/llm_taging/parser.py
notte_browser/tagging/action/llm_taging/pipe.py
notte_browser/tagging/action/llm_taging/validation.py
notte_browser/tagging/action/simple/__init__.py
notte_browser/tagging/action/simple/pipe.py
notte_browser/tools/__init__.py
notte_browser/tools/base.py
notte_browser-1.8.3.dist-info/METADATA
notte_browser-1.8.3.dist-info/WHEEL
notte_browser-1.8.3.dist-info/RECORD
