Metadata-Version: 2.4
Name: notte-browser
Version: 1.8.3
Summary: The web browser for LLMs agents
Author-email: Notte Team  <hello@notte.cc>
Requires-Python: >=3.11
Requires-Dist: maincontentextractor
Requires-Dist: markdownify>=0.14.1
Requires-Dist: notte-core==v1.8.3
Requires-Dist: notte-llm==v1.8.3
Requires-Dist: patchright~=1.55
Requires-Dist: pillow>=11.2.1
Requires-Dist: tqdm>=4.66.0
